rfmailosaur/__init__.py
rfmailosaur/keywords.py
rfmailosaur/server_management_keywords.py
rfmailosaur/version.py
robotframework_mailosaur-1.0.2.dist-info/METADATA
robotframework_mailosaur-1.0.2.dist-info/WHEEL
robotframework_mailosaur-1.0.2.dist-info/top_level.txt
robotframework_mailosaur-1.0.2.dist-info/RECORD
