Metadata-Version: 2.1
Name: robotframework-mailosaur
Version: 1.0.2
Summary: Mailosaur library for Robot framework
Home-page: https://github.com/primait/robotframework-mailosaur
Author: Prima.it
Author-email: 
Classifier: Programming Language :: Python :: 3
Classifier: License :: OSI Approved :: MIT License
Classifier: Operating System :: OS Independent
Requires-Dist: robotframework (>=4.0)
Requires-Dist: mailosaur
